volcano_cooking/__init__.py
volcano_cooking/__main__.py
volcano_cooking/configurations/shift_eruption_to_date.py
volcano_cooking/createVolcEruptV3.ncl
volcano_cooking/create_cesm_frc.sh
volcano_cooking/helper_scripts/__init__.py
volcano_cooking/helper_scripts/compare_datasets.py
volcano_cooking/helper_scripts/compare_volc_files.py
volcano_cooking/helper_scripts/functions.py
volcano_cooking/helper_scripts/inspect_X-vs-Y.py
volcano_cooking/helper_scripts/inspect_year.py
volcano_cooking/helper_scripts/view_generated_forcing.py
volcano_cooking/modules/convert/__init__.py
volcano_cooking/modules/convert/adjust_emissions_and_heights.py
volcano_cooking/modules/convert/convert_between_variables.py
volcano_cooking/modules/create/__init__.py
volcano_cooking/modules/create/create_data.py
volcano_cooking/modules/create/create_dates.py
volcano_cooking/modules/create/create_frc.py
volcano_cooking/modules/create/easy_fix.py
volcano_cooking/modules/create/rewrite_frc_file.py
volcano_cooking/package_last.sh
volcano_cooking/parse_stratvolc.py
volcano_cooking/sparse_to_lin.py
volcano_cooking/synthetic_volcanoes.py
volcano_cooking/view_force.py
volcano_cooking-1.0.0.dist-info/LICENSE
volcano_cooking-1.0.0.dist-info/METADATA
volcano_cooking-1.0.0.dist-info/WHEEL
volcano_cooking-1.0.0.dist-info/entry_points.txt
volcano_cooking-1.0.0.dist-info/RECORD
