Metadata-Version: 2.1
Name: volcano-cooking
Version: 1.0.0
Summary: Make some volcanoes and simulate them in CESM2
License: GPL-3.0-or-later
Author: engeir
Author-email: eirroleng@gmail.com
Requires-Python: >=3.9,<3.13
Classifier: License :: OSI Approved :: GNU General Public License v3 or later (GPLv3+)
Classifier: Programming Language :: Python :: 3
Classifier: Programming Language :: Python :: 3.9
Classifier: Programming Language :: Python :: 3.10
Classifier: Programming Language :: Python :: 3.11
Classifier: Programming Language :: Python :: 3.12
Requires-Dist: PyWavelets (>=1.1.1,<2.0.0)
Requires-Dist: cftime (>=1.5.0,<2.0.0)
Requires-Dist: click (>=8.0.1,<9.0.0)
Requires-Dist: cosmoplots (>=0.1.5,<0.3.0)
Requires-Dist: dask (>=2022.3,<2025.0)
Requires-Dist: importlib-metadata (>=5,<8)
Requires-Dist: matplotlib (>=3.4.2,<4.0.0)
Requires-Dist: netCDF4 (>=1.5.8,<2.0.0)
Requires-Dist: numpy (>=1.21.1,<2.0.0)
Requires-Dist: scipy (>=1.7.1,<2.0.0)
Requires-Dist: superposed-pulses (>=1.3,<2.0)
Requires-Dist: wget (>=3.2,<4.0)
Requires-Dist: xarray (>=2023.12,<2025.0)
